{
    "menu_id": "sydneyhud_hudlist_options",
    "parent_menu": "sydneyhud_menu",
    "title": "sydneyhud_hudlist_options",
    "description": "sydneyhud_hudlist_options_desc",
    "items": [
        {
            "type": "toggle",
            "id": "hudlist_enabled",
            "title": "sydneyhud_hudlist_enabled",
            "description" : "",
            "callback": "SetValue",
            "value": "hudlist_enabled",
            "default_value": true,
            "is_parent": true
        },
        {
            "type" : "divider",
            "size" : 16
        },
        {
            "type" : "button",
            "id" : "sydneyhud_hudlist_options_left",
            "title" : "sydneyhud_hudlist_options_left",
            "description" : "sydneyhud_hudlist_options_left_desc",
            "next_menu" : "sydneyhud_hudlist_options_left",
            "parent" : "hudlist_enabled"
        },
        {
            "type" : "button",
            "id" : "sydneyhud_hudlist_options_right",
            "title" : "sydneyhud_hudlist_options_right",
            "description" : "sydneyhud_hudlist_options_right_desc",
            "next_menu" : "sydneyhud_hudlist_options_right",
            "parent" : "hudlist_enabled"
        },
        {
            "type" : "button",
            "id" : "sydneyhud_hudlist_options_buff",
            "title" : "sydneyhud_hudlist_options_buff",
            "description" : "sydneyhud_hudlist_options_buff_desc",
            "next_menu" : "sydneyhud_hudlist_options_buff",
            "parent" : "hudlist_enabled"
        },
        {
            "type" : "divider",
            "size" : 16
        },
        {
            "type" : "button",
            "id" : "sydneyhud_hudlist_options_color",
            "title" : "sydneyhud_hudlist_options_color",
            "description" : "sydneyhud_hudlist_options_color_desc",
            "next_menu" : "sydneyhud_hudlist_options_color",
            "parent" : "hudlist_enabled"
        }
    ]
}